LICENSE
MANIFEST.in
README.md
pyproject.toml
requirements.txt
robustAI/__init__.py
robustAI/advertrain/__init__.py
robustAI/advertrain/constants.py
robustAI/advertrain/metrics.py
robustAI/advertrain/models.py
robustAI/advertrain/transforms.py
robustAI/advertrain/dependencies/__init__.py
robustAI/advertrain/dependencies/autoattack.py
robustAI/advertrain/dependencies/dropblock.py
robustAI/advertrain/dependencies/fire.py
robustAI/advertrain/dependencies/trades.py
robustAI/advertrain/dependencies/cleverhans/__init__.py
robustAI/advertrain/dependencies/cleverhans/fast_gradient_method.py
robustAI/advertrain/dependencies/cleverhans/projected_gradient_descent.py
robustAI/advertrain/dependencies/cleverhans/utils.py
robustAI/advertrain/training/__init__.py
robustAI/advertrain/training/adversarial_training.py
robustAI/advertrain/training/autoattack_training.py
robustAI/advertrain/training/classical_training.py
robustAI/advertrain/training/fire_training.py
robustAI/advertrain/training/trades_training.py
robust_ai.egg-info/PKG-INFO
robust_ai.egg-info/SOURCES.txt
robust_ai.egg-info/dependency_links.txt
robust_ai.egg-info/requires.txt
robust_ai.egg-info/top_level.txt