Metadata-Version: 2.4
Name: robust-ai
Version: 0.1.2
Summary: Robustness library for binary image classification tasks
Author: IRT-SystemX.fr
Author-email: support@irt-systemx.fr
License-Expression: Apache-2.0
Project-URL: Homepage, https://irt-systemx.github.io/robust-ai
Project-URL: Documentation, https://irt-systemx.github.io/robust-ai
Project-URL: Repository, https://github.com/IRT-SystemX/robust-ai
Requires-Python: <3.11,>=3.9
License-File: LICENSE
Requires-Dist: numpy==1.26.2
Requires-Dist: pandas==2.1.4
Requires-Dist: pytest==7.4.3
Requires-Dist: torch==1.13.1
Requires-Dist: torchvision==0.14.1
Requires-Dist: tqdm==4.66.1
Requires-Dist: typing_extensions==4.8.0
Requires-Dist: nvidia-cublas-cu11==11.10.3.66
Requires-Dist: nvidia-cuda-nvrtc-cu11==11.7.99
Requires-Dist: nvidia-cuda-runtime-cu11==11.7.99
Requires-Dist: nvidia-cudnn-cu11==8.5.0.96
Dynamic: license-file
